LICENSE
MANIFEST.in
README
setup.py
nodevers/__init__.py
nodevers/__main__.py
nodevers/cli.py
nodevers/install.py
nodevers/install_helper.py
nodevers/remove.py
nodevers/shared.py
nodevers/use.py
nodevers/version.py
nodevers/versions.py
nodevers.egg-info/PKG-INFO
nodevers.egg-info/SOURCES.txt
nodevers.egg-info/dependency_links.txt
nodevers.egg-info/top_level.txt
scripts/nodevers