Metadata-Version: 1.1
Name: nodevers
Version: 0.2.1
Summary: Node.js version manager
Home-page: https://github.com/keremc/nodevers
Author: Kerem Çakırer
Author-email: kcakirer@hotmail.com
License: BSD (3-Clause) License
Platform: UNKNOWN
Classifier: Development Status :: 4 - Beta
Classifier: Intended Audience :: Developers
Classifier: License :: OSI Approved :: BSD License
Classifier: Operating System :: POSIX :: Linux
Classifier: Programming Language :: Python :: 2
Classifier: Programming Language :: Python :: 2.6
Classifier: Programming Language :: Python :: 2.7
Classifier: Programming Language :: Python :: Implementation :: CPython
Classifier: Topic :: Software Development
Classifier: Topic :: Utilities
